opsorchestrator/__init__.py
opsorchestrator/contracts/__init__.py
opsorchestrator/contracts/opsorchestrator.py
opsorchestrator/core/__init__.py
opsorchestrator/core/data_source/__init__.py
opsorchestrator/core/decorator/__init__.py
opsorchestrator/core/decorator/class_decorators.py
opsorchestrator/core/decorator/rbac.py
opsorchestrator/core/events/__init__.py
opsorchestrator/core/execution_unit/__init__.py
opsorchestrator/core/model/__init__.py
opsorchestrator/core/model/component.py
opsorchestrator/core/model/data/__init__.py
opsorchestrator/core/model/data/data_element.py
opsorchestrator/core/model/data/precondition.py
opsorchestrator/core/model/element.py
opsorchestrator/core/model/intent/__init__.py
opsorchestrator/core/model/intent/intent_element.py
opsorchestrator/core/model/technology.py
opsorchestrator/core/operation/__init__.py
opsorchestrator/logger/__init__.py
opsorchestrator/logger/local.py
opsorchestrator_microsoft_xdr/__init__.py
opsorchestrator_microsoft_xdr/contracts/__init__.py
opsorchestrator_microsoft_xdr/contracts/mde.py
opsorchestrator_servicenow/__init__.py
opsorchestrator_servicenow/contracts/__init__.py
opsorchestrator_servicenow/contracts/servicenow.py
opsorchestrator_zscaler/__init__.py
opsorchestrator_zscaler/contracts/__init__.py
opsorchestrator_zscaler/contracts/datalake.py
opsorchestrator_zscaler/contracts/generic.py
opsorchestrator_zscaler/contracts/zscaler.py
opsorchestrator_sdk-1.0.6.dist-info/METADATA
opsorchestrator_sdk-1.0.6.dist-info/WHEEL
opsorchestrator_sdk-1.0.6.dist-info/RECORD
