Metadata-Version: 2.4
Name: opsorchestrator-sdk
Version: 1.0.6
Summary: OpsOrchestrator SDK
License: MIT
Author: SLE Software Engineering Team in Cairo
Requires-Python: >=3.14,<4.0
Classifier: License :: OSI Approved :: MIT License
Classifier: Programming Language :: Python :: 3
Classifier: Programming Language :: Python :: 3.14
Requires-Dist: bcrypt
Requires-Dist: beautifulsoup4
Requires-Dist: cryptography
Requires-Dist: datalake-scripts
Requires-Dist: flask
Requires-Dist: flask-cors
Requires-Dist: flask-jwt-extended
Requires-Dist: flask-limiter
Requires-Dist: flask-migrate
Requires-Dist: flask-restx
Requires-Dist: flask-socketio
Requires-Dist: flask-sqlalchemy
Requires-Dist: ldap3
Requires-Dist: passlib
Requires-Dist: psycopg2-binary
Requires-Dist: pyjwt
Requires-Dist: python-dotenv
Requires-Dist: pyyaml
Requires-Dist: redis
Requires-Dist: requests
Requires-Dist: tldextract
Requires-Dist: werkzeug
